pexels/__init__.py
pexels/pexels.py
pexels/models/__init__.py
pexels/models/enums/__init__.py
pexels/models/enums/orientation.py
pexels/models/enums/size.py
pexels-0.0.11.dist-info/LICENSE
pexels-0.0.11.dist-info/METADATA
pexels-0.0.11.dist-info/WHEEL
pexels-0.0.11.dist-info/top_level.txt
pexels-0.0.11.dist-info/RECORD
